pypoolsync/__init__.py
pypoolsync/const.py
pypoolsync/exceptions.py
pypoolsync/poolsync.py
pypoolsync/py.typed
pypoolsync/utils.py
pypoolsync-0.1.5.dist-info/LICENSE
pypoolsync-0.1.5.dist-info/METADATA
pypoolsync-0.1.5.dist-info/WHEEL
pypoolsync-0.1.5.dist-info/RECORD
